consoleoptions.py
consoleoptions-1.1.0.dist-info/LICENSE
consoleoptions-1.1.0.dist-info/METADATA
consoleoptions-1.1.0.dist-info/WHEEL
consoleoptions-1.1.0.dist-info/entry_points.txt
consoleoptions-1.1.0.dist-info/top_level.txt
consoleoptions-1.1.0.dist-info/RECORD
