Metadata-Version: 2.1
Name: consoleoptions
Version: 1.1.0
Summary: Create Console Option Dictionary
Home-page: https://github.com/yknaka/consoleoptions
Author: Yuki NAKAMURA
Author-email: naka_yk@live.jp
License: UNKNOWN
Project-URL: Create Console Option Dictionary, https://github.com/yknaka/consoleoptions
Platform: UNKNOWN
Classifier: Programming Language :: Python :: 3
Classifier: License :: OSI Approved :: MIT License
Classifier: Operating System :: OS Independent
Requires-Python: >=3.6
License-File: LICENSE
